cPyExtPatt/__init__.py
cPyExtPatt/cCtxMgr.cpython-312-darwin.so
cPyExtPatt/cExceptions.cpython-312-darwin.so
cPyExtPatt/cFile.cpython-312-darwin.so
cPyExtPatt/cModuleGlobals.cpython-312-darwin.so
cPyExtPatt/cObject.cpython-312-darwin.so
cPyExtPatt/cParseArgs.cpython-312-darwin.so
cPyExtPatt/cParseArgsHelper.cpython-312-darwin.so
cPyExtPatt/cPickle.cpython-312-darwin.so
cPyExtPatt/cPyRefs.cpython-312-darwin.so
cPyExtPatt/cRefCount.cpython-312-darwin.so
cPyExtPatt/cSeqObject.cpython-312-darwin.so
cPyExtPatt/cStructSequence.cpython-312-darwin.so
cPyExtPatt/cWatchers.cpython-312-darwin.so
cPyExtPatt/Capsules/datetimetz.cpython-312-darwin.so
cPyExtPatt/Capsules/spam.cpython-312-darwin.so
cPyExtPatt/Capsules/spam_capsule.cpython-312-darwin.so
cPyExtPatt/Capsules/spam_client.cpython-312-darwin.so
cPyExtPatt/Iterators/cIterator.cpython-312-darwin.so
cPyExtPatt/Logging/cLogging.cpython-312-darwin.so
cPyExtPatt/SimpleExample/cFibA.cpython-312-darwin.so
cPyExtPatt/SimpleExample/cFibB.cpython-312-darwin.so
cPyExtPatt/SubClass/sublist.cpython-312-darwin.so
cPyExtPatt/Threads/cppsublist.cpython-312-darwin.so
cPyExtPatt/Threads/csublist.cpython-312-darwin.so
cPyExtPatt/cpp/cUnicode.cpython-312-darwin.so
cPyExtPatt/cpp/placement_new.cpython-312-darwin.so
cpyextpatt-0.3.0.dist-info/licenses/LICENSE.txt
cpyextpatt-0.3.0.dist-info/METADATA
cpyextpatt-0.3.0.dist-info/WHEEL
cpyextpatt-0.3.0.dist-info/top_level.txt
cpyextpatt-0.3.0.dist-info/RECORD
